dflipflop.sv
 /**
  * File: dflipflop.sv
  *
  * Author1:  Nathan Fox (njfox4@buffalo.edo)
  * Author2:
  * Date:     2023-5-08
  * Partner:  N/A
  * Course:   CSE241 - Digital Systems
  *
  * Summary of File:
  * 
  * This file implements the basic functionality of a dflip-flop.  It has the inputs 
  * D and CLK and outputs.  Heavily based on the code from lecture 31.  D is D, CLK is the
  * clock input, Q is output.  Clear, Preset, and Q0 (Qnot) are not required for the purposes of this project.
  */



module dflipflop(D, CLK, Q);

  input D, CLK;
  output Q; reg Q;
  
  initial
    begin
      Q = 0;
    end

  always@(posedge CLK)
    begin
      Q = D;
    end


endmodule

dff-tb.sv
 /**
  * File: dff-tb.sv
  *
  * Author1:  Nathan Fox (njfox4@buffalo.edo)
  * Author2:
  * Date:     2023-5-08
  * Partner:  N/A
  * Course:   CSE241 - Digital Systems
  *
  * Summary of File:
  * 
  *   Test the flip-flop, should be pretty self explanatory.
  */

  module dfftb;

  reg dtb, clk;
  wire qtb;

  dflipflop dff(dtb, clk, qtb);

  initial 
    begin
      $dumpfile("dff.vcd");
      $dumpvars;
      // standard test bench stuff, display vars, init everything, set up finish.  not much to say
      dtb = 0;
      clk = 0;
      $display("dtb \t clk |   qtb");
      $monitor(" %d  \t  %d  |    %d",dtb,clk,qtb);
     

      #15 $finish;
    end

  always
    begin
      #1 dtb = 1; clk = ~clk;
      #1 dtb = 0; clk = ~clk;
      #1 clk = ~clk;
    end

endmodule

dff.vcd
$date
	Fri May 12 09:59:08 2023
$end
$version
	Icarus Verilog
$end
$timescale
	1s
$end
$scope module dfftb $end
$var wire 1 ! qtb $end
$var reg 1 " clk $end
$var reg 1 # dtb $end
$scope module dff $end
$var wire 1 " CLK $end
$var wire 1 # D $end
$var reg 1 ! Q $end
$upscope $end
$upscope $end
$enddefinitions $end
$comment Show the parameter values. $end
$dumpall
$end
#0
$dumpvars
0#
0"
0!
$end
#1
1!
1"
1#
#2
0"
0#
#3
0!
1"
#4
0"
1#
#5
1"
0#
#6
0"
#7
1!
1"
1#
#8
0"
0#
#9
0!
1"
#10
0"
1#
#11
1"
0#
#12
0"
#13
1!
1"
1#
#14
0"
0#
#15
0!
1"
