test.sv
`define thing 'b1111




module test(arr, out);


  
  input reg[3:0] arr;
  output reg[3:0] out = 'b0111;


  always
    begin
        #1
        out = arr ~^ out;
        case(out)
        `thing : 
          begin
            $display("boo");
          end
          default : $display("oob");
        endcase

        `ifdef thing
          out = ~out;
        `endif
    end



endmodule

testtb.sv
`define thing 'b1111

module testtb;

  reg[3:0] arr_tb;
  wire[3:0] out_tb;

  // Instantiate the design module
  test tb(arr_tb, out_tb);

  // Add testbench logic
  initial begin
    // Drive inputs
    arr_tb = 4'b0111;

    // Display outputs
    $monitor("arr = %b, out = %b", tb.arr, tb.out);


    $dumpfile("testfile.vcd");
    $dumpvars(0, testtb);
    

    #18 $finish;
  end

endmodule

testfile.vcd
$date
	Tue May  9 17:18:04 2023
$end
$version
	Icarus Verilog
$end
$timescale
	1s
$end
$scope module testtb $end
$var wire 4 ! out_tb [3:0] $end
$var reg 4 " arr_tb [3:0] $end
$scope module tb $end
$var wire 4 # arr [3:0] $end
$var reg 4 $ out [3:0] $end
$upscope $end
$upscope $end
$enddefinitions $end
$comment Show the parameter values. $end
$dumpall
$end
#0
$dumpvars
b111 $
b111 #
b111 "
b111 !
$end
#1
b1111 !
b1111 $
#2
b111 !
b111 $
#3
b1111 !
b1111 $
#4
b111 !
b111 $
#5
b1111 !
b1111 $
#6
b111 !
b111 $
#7
b1111 !
b1111 $
#8
b111 !
b111 $
#9
b1111 !
b1111 $
#10
b111 !
b111 $
#11
b1111 !
b1111 $
#12
b111 !
b111 $
#13
b1111 !
b1111 $
#14
b111 !
b111 $
#15
b1111 !
b1111 $
#16
b111 !
b111 $
#17
b1111 !
b1111 $
#18
b111 !
b111 $
